<?xml version="1.0" encoding="UTF-8"?>
<package xmlns="http://expath.org/ns/pkg" name="http://eNahar.org/ns/lib/memops" abbrev="memops" version="0.2.0" spec="1.0">
    <title>Memory Operations</title>
    <xquery>
        <namespace>http://eNahar.org/ns/lib/mem</namespace>
        <file>memory-operations-pure-xquery.xqy</file>
    </xquery>
    <xquery>
        <namespace>http://eNahar.org/ns/lib/nodeops</namespace>
        <file>node-operations.xqy</file>
    </xquery>
    <xquery>
        <namespace>http://eNahar.org/ns/lib/memops</namespace>
        <file>memory-operations.xqy</file>
    </xquery>
</package>
